plone/app/tiles/__init__.py
plone/app/tiles/configure.zcml
plone/app/tiles/demo.py
plone/app/tiles/demo.zcml
plone/app/tiles/drafting.py
plone/app/tiles/handlers.py
plone/app/tiles/imagescaling.py
plone/app/tiles/interfaces.py
plone/app/tiles/modifiers.py
plone/app/tiles/setuphandlers.py
plone/app/tiles/testing.py
plone/app/tiles/utils.py
plone/app/tiles/vocabularies.py
plone/app/tiles/browser/__init__.py
plone/app/tiles/browser/add.pt
plone/app/tiles/browser/add.py
plone/app/tiles/browser/base.py
plone/app/tiles/browser/configure.zcml
plone/app/tiles/browser/delete.py
plone/app/tiles/browser/download.py
plone/app/tiles/browser/edit.py
plone/app/tiles/browser/layout.pt
plone/app/tiles/browser/tileformlayout.pt
plone/app/tiles/browser/traversal.py
plone/app/tiles/browser/wrapper.pt
plone/app/tiles/locales/plone.pot
plone/app/tiles/locales/es/LC_MESSAGES/plone.mo
plone/app/tiles/locales/es/LC_MESSAGES/plone.po
plone/app/tiles/locales/it/LC_MESSAGES/plone.mo
plone/app/tiles/locales/it/LC_MESSAGES/plone.po
plone/app/tiles/locales/pt_BR/LC_MESSAGES/plone.mo
plone/app/tiles/locales/pt_BR/LC_MESSAGES/plone.po
plone/app/tiles/profiles/default/browserlayer.xml
plone/app/tiles/profiles/default/metadata.xml
plone/app/tiles/profiles/default/plone.app.tiles_default.txt
plone/app/tiles/profiles/default/registry.xml
plone/app/tiles/profiles/demo/metadata.xml
plone/app/tiles/profiles/demo/registry/tiles.xml
plone/app/tiles/tests/__init__.py
plone/app/tiles/tests/_test_drafting.py
plone/app/tiles/tests/test_forms.py
plone/app/tiles/tests/test_imagescaling.py
plone/app/tiles/tests/test_lifecycle.py
plone/app/tiles/tests/test_modifiers.py
plone/app/tiles/tests/test_traversal.py
plone/app/tiles/tests/test_vocabularies.py
plone/app/tiles/www/CleanTileAnnotations.pt
plone/app/tiles/www/modifier.gif
plone_app_tiles-5.0.0.dist-info/licenses/LICENSE.GPL
plone_app_tiles-5.0.0.dist-info/licenses/LICENSE.txt
plone_app_tiles-5.0.0.dist-info/METADATA
plone_app_tiles-5.0.0.dist-info/WHEEL
plone_app_tiles-5.0.0.dist-info/top_level.txt
plone_app_tiles-5.0.0.dist-info/RECORD
