Metadata-Version: 2.4
Name: plone.app.tiles
Version: 5.0.0
Summary: Plone UI integration for plone.tiles
Home-page: https://github.com/plone/plone.app.tiles
Author: Martin Aspeli
Author-email: optilude@gmail.com
Keywords: plone tiles deco
Classifier: Development Status :: 5 - Production/Stable
Classifier: Environment :: Web Environment
Classifier: Framework :: Plone
Classifier: Framework :: Plone :: 6.2
Classifier: Framework :: Plone :: Addon
Classifier: License :: OSI Approved :: GNU General Public License v2 (GPLv2)
Classifier: Programming Language :: Python
Classifier: Programming Language :: Python :: 3.10
Classifier: Programming Language :: Python :: 3.11
Classifier: Programming Language :: Python :: 3.12
Classifier: Programming Language :: Python :: 3.13
Classifier: Topic :: Internet :: WWW/HTTP
Classifier: Topic :: Internet :: WWW/HTTP :: Dynamic Content
Classifier: Topic :: Software Development :: Libraries :: Python Modules
Requires-Python: >=3.10
License-File: LICENSE.GPL
License-File: LICENSE.txt
Requires-Dist: setuptools
Requires-Dist: zope.annotation
Requires-Dist: zope.i18nmessageid
Requires-Dist: plone.namedfile>=6.0.0a3
Requires-Dist: plone.memoize
Requires-Dist: plone.registry
Requires-Dist: plone.scale>=4.0.1
Requires-Dist: plone.tiles
Requires-Dist: zope.publisher
Requires-Dist: zope.security
Requires-Dist: zope.component
Requires-Dist: zope.interface
Requires-Dist: plone.z3cform
Requires-Dist: plone.autoform
Requires-Dist: z3c.form
Requires-Dist: plone.uuid
Requires-Dist: Products.statusmessages
Requires-Dist: zope.traversing
Requires-Dist: zope.event
Requires-Dist: zope.lifecycleevent
Requires-Dist: zope.schema
Requires-Dist: Zope
Requires-Dist: AccessControl
Provides-Extra: test
Requires-Dist: Pillow; extra == "test"
Requires-Dist: plone.app.drafts; extra == "test"
Requires-Dist: plone.app.relationfield; extra == "test"
Requires-Dist: plone.app.testing; extra == "test"
Requires-Dist: plone.dexterity; extra == "test"
Requires-Dist: plone.app.dexterity; extra == "test"
Dynamic: author
Dynamic: author-email
Dynamic: classifier
Dynamic: description
Dynamic: home-page
Dynamic: keywords
Dynamic: license-file
Dynamic: provides-extra
Dynamic: requires-dist
Dynamic: requires-python
Dynamic: summary
